README.rst
setup.cfg
setup.py
pymongo_document/__init__.py
pymongo_document/conf.py
pymongo_document/documents.py
pymongo_document/errors.py
pymongo_document/helpers.py
pymongo_document/running-number.py
pymongo_document_modeling.egg-info/PKG-INFO
pymongo_document_modeling.egg-info/SOURCES.txt
pymongo_document_modeling.egg-info/dependency_links.txt
pymongo_document_modeling.egg-info/requires.txt
pymongo_document_modeling.egg-info/top_level.txt