Metadata-Version: 1.1
Name: pymongo-document-modeling
Version: 0.9.1.dev4
Summary: PyMongo data modeling library
Home-page: https://github.com/peatiscoding/pymongo-document-modeling
Author: peatiscoding
Author-email: freeuxer@gmail.com
License: Apache License, Version 2.0
Keywords: pymongo,database,mongodb,modeling
Platform: UNKNOWN
Classifier: Development Status :: 2 - Pre-Alpha
Classifier: Intended Audience :: Developers
Classifier: Natural Language :: English
Classifier: Programming Language :: Python :: 2.7
Classifier: Topic :: Database
Classifier: Topic :: Software Development :: Libraries
